{
  "raised": 10419,
  "goal": 20000,
  "donors": 70,
  "last_updated": "2026-04-02",
  "recent_donors": [
    {
      "date": "2026-03-27 21:20:28",
      "amount": 5412,
      "amount_display": "$54",
      "name": "Ellie L",
      "message": ""
    },
    {
      "date": "2026-03-22 08:52:10",
      "amount": 13188,
      "amount_display": "$132",
      "name": "Bestie and Henry Cadalt",
      "message": "Good Luck Boys! Bestie and Henry!"
    },
    {
      "date": "2026-01-22 21:50:15",
      "amount": 8025,
      "amount_display": "$80",
      "name": "Lisa Smith (Powell)",
      "message": "Good luck!!!"
    },
    {
      "date": "2026-02-02 18:57:12",
      "amount": 12500,
      "amount_display": "$125",
      "name": "Marg Sharkey",
      "message": "Well done Ethan"
    },
    {
      "date": "2026-02-02 19:52:51",
      "amount": 21100,
      "amount_display": "$211",
      "name": "Denise Thompson",
      "message": "So very proud of you both xx"
    },
    {
      "date": "2026-03-14 10:37:00",
      "amount": 5412,
      "amount_display": "$54",
      "name": "Danielle & Warwick Campbell",
      "message": "What an amazing, awesome and selfless thing to do"
    },
    {
      "date": "2026-02-03 13:03:23",
      "amount": 3315,
      "amount_display": "$33",
      "name": "Elaine & Phil",
      "message": "Such a great cause Ethan and Austin. Good on you both. \ud83d\udc4f Lots of luck."
    },
    {
      "date": "2026-02-02 22:33:01",
      "amount": 5412,
      "amount_display": "$54",
      "name": "Noah & Kate Wilkinson",
      "message": "Goodluck Boys \ud83c\udf1f"
    }
  ]
}